mcrf/__init__.py
mcrf/metrics.py
mcrf/helper/__init__.py
mcrf/helper/collate_function.py
mcrf/helper/dataset.py
mcrf/helper/label_encoder.py
mcrf/helper/manager.py
mcrf/helper/transform.py
mcrf/helper/vocab.py
mcrf/models/__init__.py
mcrf/models/lstm_crf.py
mcrf/modules/__init__.py
mcrf/modules/constraint.py
mcrf/modules/masked.py
mcrf/modules/plain.py
mcrf/tasks/__init__.py
mcrf/tasks/base_task.py
mcrf/tasks/ner.py
mcrf/utils/__init__.py
mcrf/utils/config.py
mcrf/utils/logging.py
pytorch_mcrf-0.0.3.dist-info/LICENSE
pytorch_mcrf-0.0.3.dist-info/METADATA
pytorch_mcrf-0.0.3.dist-info/WHEEL
pytorch_mcrf-0.0.3.dist-info/top_level.txt
pytorch_mcrf-0.0.3.dist-info/RECORD
