Metadata-Version: 2.1
Name: pytorch-mcrf
Version: 0.0.3
Summary: Multiple CRF implementation for PyTorch
Home-page: UNKNOWN
Author: Tong Zhu
Author-email: tzhu1997@outlook.com
License: UNKNOWN
Platform: UNKNOWN
Classifier: Programming Language :: Python :: 3
Classifier: License :: OSI Approved :: MIT License
Requires-Python: >=3.6
